aad_client/__init__.py
aad_client/_version.py
aad_client/authorisation.py
aad_client-0.0.1.dist-info/LICENSE
aad_client-0.0.1.dist-info/METADATA
aad_client-0.0.1.dist-info/WHEEL
aad_client-0.0.1.dist-info/top_level.txt
aad_client-0.0.1.dist-info/RECORD
